grocery/__init__.py
grocery/builtins_ext.py
grocery/date_utils.py
grocery/helper.py
grocery-1.4.6.dist-info/LICENSE
grocery-1.4.6.dist-info/METADATA
grocery-1.4.6.dist-info/WHEEL
grocery-1.4.6.dist-info/top_level.txt
grocery-1.4.6.dist-info/RECORD
