Metadata-Version: 2.1
Name: grocery
Version: 1.4.6
Summary: A grocery helper
Home-page: https://github.com/mrene327/grocery
Author: Wenlong Chen
Author-email: mrene327@gmail.com
License: MIT
Classifier: License :: OSI Approved :: MIT License
Classifier: Operating System :: OS Independent
Classifier: Programming Language :: Python :: 3 :: Only
License-File: LICENSE
